{"chunk_definitions":[{"row":9,"row_count":1,"visible":true,"expansion_state":0,"options":{"engine":"r","label":"setup","include":false,"dev":"png"},"document_id":"D52BD772","chunk_id":"csetup_chunk","chunk_label":"setup"},{"row":16,"row_count":1,"visible":true,"expansion_state":0,"options":{"engine":"r","label":"unnamed-chunk-2","dev":"png"},"document_id":"D52BD772","chunk_id":"cfduhpmqxe1o9","chunk_label":"unnamed-chunk-1"}],"doc_write_time":1738764192,"working_dir":null,"default_chunk_options":{"echo":true}}